LICENSE
LICENSE.txt
README.rst
setup.cfg
setup.py
OCR_GLS_G6/OcrMulti.py
OCR_GLS_G6/OcrTools.py
OCR_GLS_G6/__init__.py
OCR_GLS_G6.egg-info/PKG-INFO
OCR_GLS_G6.egg-info/SOURCES.txt
OCR_GLS_G6.egg-info/dependency_links.txt
OCR_GLS_G6.egg-info/requires.txt
OCR_GLS_G6.egg-info/top_level.txt