Metadata-Version: 2.1
Name: OCR-GLS-G6
Version: 1.0
Summary: OCR_GLS_G6 - Optical character recognition and QR codes. Support Multiple PDF page file.
Home-page: https://git.bdms.co.th/Burin.Pa/ocr_gls_g6
Author: Burin Panchat
Author-email: burin.gbp@gmail.com
License: MIT
Download-URL: https://git.bdms.co.th/Burin.Pa/ocr_gls_g6/-/blob/master/dist/ocr_gls_g6.zip
Keywords: OCR_GLS_G6,OCR,ocr
Platform: UNKNOWN
Classifier: Development Status :: 3 - Alpha
Classifier: Intended Audience :: Developers
Classifier: Topic :: Documentation
Classifier: License :: OSI Approved :: MIT License
Classifier: Programming Language :: Python :: 3.7
License-File: LICENSE
License-File: LICENSE.txt
